yesapi/__init__.py
yesapi-1.0.2.dist-info/LICENSE
yesapi-1.0.2.dist-info/METADATA
yesapi-1.0.2.dist-info/WHEEL
yesapi-1.0.2.dist-info/top_level.txt
yesapi-1.0.2.dist-info/RECORD
