Metadata-Version: 2.1
Name: yesapi
Version: 1.0.2
Summary: yesapi-python3-sdk
Home-page: https://github.com/asihacker/yesapi
Author: chenjunxue
Author-email: asihacker@gmail.com
License: MIT license
Keywords: yesapi,api,yes
Platform: UNKNOWN
Classifier: Programming Language :: Python :: 3
Classifier: License :: OSI Approved :: MIT License
Classifier: Operating System :: OS Independent
License-File: LICENSE
Requires-Dist: requests
